pytest_fixture_tools/__init__.py
pytest_fixture_tools/plugin.py
pytest_fixture_tools-1.2.1.dist-info/licenses/LICENSE.txt
pytest_fixture_tools-1.2.1.dist-info/METADATA
pytest_fixture_tools-1.2.1.dist-info/WHEEL
pytest_fixture_tools-1.2.1.dist-info/entry_points.txt
pytest_fixture_tools-1.2.1.dist-info/top_level.txt
pytest_fixture_tools-1.2.1.dist-info/RECORD
